aioflows/__init__.py
aioflows/core.py
aioflows/mqtt.py
aioflows/network.py
aioflows/simple.py
aioflows/stdio.py
aioflows/thread.py
aioflows/zeroconf.py
examples/list.py
examples/minimal.py
examples/mqtt.py
examples/ssdp-listener.py
examples/thread.py
examples/ticker.py
examples/udp-echo.py
examples/attic/alice.py
aioflows-0.2.0.dist-info/LICENSE
aioflows-0.2.0.dist-info/METADATA
aioflows-0.2.0.dist-info/WHEEL
aioflows-0.2.0.dist-info/top_level.txt
aioflows-0.2.0.dist-info/zip-safe
aioflows-0.2.0.dist-info/RECORD
