Metadata-Version: 2.1
Name: aioflows
Version: 0.2.0
Summary: Python data flows library to build structured applications
Author-email: Anton Patrushev <apatrushev@gmail.com>
License: MIT
Project-URL: Source, https://github.com/apatrushev/aioflows
Project-URL: Tracker, https://github.com/apatrushev/aioflows/issues
Classifier: Development Status :: 2 - Pre-Alpha
Classifier: Framework :: AsyncIO
Classifier: Intended Audience :: Developers
Classifier: License :: OSI Approved :: MIT License
Classifier: Operating System :: OS Independent
Classifier: Programming Language :: Python :: 3 :: Only
Classifier: Programming Language :: Python :: 3.8
Classifier: Programming Language :: Python :: 3.9
Classifier: Programming Language :: Python :: 3.10
Classifier: Programming Language :: Python :: 3.11
Classifier: Programming Language :: Python :: Implementation :: CPython
Classifier: Programming Language :: Python
Classifier: Topic :: Software Development :: Libraries
Requires-Python: >=3.8
License-File: LICENSE
Requires-Dist: janus
Requires-Dist: pydantic <2.5,>=2.4.1
Provides-Extra: dev
Requires-Dist: pytest-asyncio ; extra == 'dev'
Requires-Dist: spherical-dev[dev] <0.4,>=0.3.0 ; extra == 'dev'
Provides-Extra: examples
Requires-Dist: aioconsole ; extra == 'examples'
Requires-Dist: aiohttp ; extra == 'examples'
Requires-Dist: aiomqtt ; extra == 'examples'
Requires-Dist: requests ; extra == 'examples'
Requires-Dist: zeroconf ; extra == 'examples'
Provides-Extra: release
Requires-Dist: spherical-dev[release] <0.4,>=0.3.4 ; extra == 'release'
